dj_dynamic_templates/__init__.py
dj_dynamic_templates/admin.py
dj_dynamic_templates/apps.py
dj_dynamic_templates/forms.py
dj_dynamic_templates/management/__init__.py
dj_dynamic_templates/management/commands/__init__.py
dj_dynamic_templates/management/commands/sync_templates.py
dj_dynamic_templates/migrations/0001_initial.py
dj_dynamic_templates/migrations/__init__.py
dj_dynamic_templates/models.py
dj_dynamic_templates/templates/category_change_form.html
dj_dynamic_templates/templates/template_change_form.html
dj_dynamic_templates/views.py
dj_dynamic_templates-1.1.3.dist-info/LICENSE
dj_dynamic_templates-1.1.3.dist-info/METADATA
dj_dynamic_templates-1.1.3.dist-info/WHEEL
dj_dynamic_templates-1.1.3.dist-info/RECORD
