Metadata-Version: 2.1
Name: dj_dynamic_templates
Version: 1.1.3
Summary: 
Author: sudheerkumar
Author-email: v.sudheerkumar91@gmail.com
Requires-Python: >=3.10,<4.0
Classifier: Programming Language :: Python :: 3
Classifier: Programming Language :: Python :: 3.10
Classifier: Programming Language :: Python :: 3.11
Classifier: Programming Language :: Python :: 3.12
Requires-Dist: django (==5.0.1)
